{
  "schema": "fleetsim.model_architecture_ir.v0",
  "model": {
    "id": "nvidia_llama_3_1_nemotron_nano_4b_v1_1_145584ad",
    "name": "nvidia/Llama-3.1-Nemotron-Nano-4B-v1.1",
    "hf_name": "nvidia/Llama-3.1-Nemotron-Nano-4B-v1.1",
    "base_model": "nvidia/Llama-3.1-Nemotron-Nano-4B-v1.1",
    "artifact_name": "Llama 3.1 Nemotron Nano 4B v1.1",
    "repo": "bartowski/nvidia_Llama-3.1-Nemotron-Nano-4B-v1.1-GGUF",
    "file": "nvidia_Llama-3.1-Nemotron-Nano-4B-v1.1-Q4_K_M.gguf",
    "architecture": "llama",
    "source_format": "gguf",
    "source": "https://huggingface.co/bartowski/nvidia_Llama-3.1-Nemotron-Nano-4B-v1.1-GGUF/resolve/main/nvidia_Llama-3.1-Nemotron-Nano-4B-v1.1-Q4_K_M.gguf",
    "parameter_count": 4512746560
  },
  "dimensions": {
    "vocab_size": 128256,
    "context_length": 131072,
    "hidden_size": 3072,
    "num_blocks": 32,
    "num_attention_heads": 32,
    "num_kv_heads": 8,
    "head_dim": 128,
    "value_head_dim": 128,
    "intermediate_size": 9216
  },
  "embeddings": [
    {
      "op": "embedding",
      "name": "token_embedding",
      "parameters": [
        {
          "name": "token_embd.weight",
          "shape": [
            3072,
            128256
          ],
          "parameter_count": 394002432
        }
      ]
    },
    {
      "op": "rope_frequencies",
      "name": "rope_freqs",
      "parameters": [
        {
          "name": "rope_freqs.weight",
          "shape": [
            64
          ],
          "parameter_count": 64
        }
      ]
    }
  ],
  "blocks": {
    "count": 32,
    "ranges": [
      {
        "range": [
          0,
          31
        ],
        "layout": [
          {
            "op": "rms_norm",
            "name": "attention_norm",
            "parameters": [
              {
                "name": "blk.N.attn_norm.weight",
                "shape": [
                  3072
                ],
                "parameter_count": 3072
              }
            ]
          },
          {
            "op": "self_attention",
            "name": "attention",
            "config": {
              "num_heads": 32,
              "num_kv_heads": 8,
              "head_dim": 128,
              "rope": true
            },
            "parameters": [
              {
                "name": "blk.N.attn_q.weight",
                "shape": [
                  3072,
                  4096
                ],
                "parameter_count": 12582912
              },
              {
                "name": "blk.N.attn_k.weight",
                "shape": [
                  3072,
                  1024
                ],
                "parameter_count": 3145728
              },
              {
                "name": "blk.N.attn_v.weight",
                "shape": [
                  3072,
                  1024
                ],
                "parameter_count": 3145728
              },
              {
                "name": "blk.N.attn_output.weight",
                "shape": [
                  4096,
                  3072
                ],
                "parameter_count": 12582912
              }
            ]
          },
          {
            "op": "residual_add",
            "name": "attention_residual"
          },
          {
            "op": "rms_norm",
            "name": "ffn_norm",
            "parameters": [
              {
                "name": "blk.N.ffn_norm.weight",
                "shape": [
                  3072
                ],
                "parameter_count": 3072
              }
            ]
          },
          {
            "op": "mlp",
            "name": "feed_forward",
            "config": {
              "activation": "silu",
              "gating": "swiglu"
            },
            "parameters": [
              {
                "name": "blk.N.ffn_gate.weight",
                "shape": [
                  3072,
                  9216
                ],
                "parameter_count": 28311552
              },
              {
                "name": "blk.N.ffn_up.weight",
                "shape": [
                  3072,
                  9216
                ],
                "parameter_count": 28311552
              },
              {
                "name": "blk.N.ffn_down.weight",
                "shape": [
                  9216,
                  3072
                ],
                "parameter_count": 28311552
              }
            ]
          },
          {
            "op": "residual_add",
            "name": "ffn_residual"
          }
        ],
        "per_block_parameter_count": 116398080,
        "total_parameter_count": 3724738560
      }
    ],
    "total_parameter_count": 3724738560
  },
  "output": [
    {
      "op": "rms_norm",
      "name": "output_norm",
      "parameters": [
        {
          "name": "output_norm.weight",
          "shape": [
            3072
          ],
          "parameter_count": 3072
        }
      ]
    },
    {
      "op": "linear",
      "name": "lm_head",
      "parameters": [
        {
          "name": "output.weight",
          "shape": [
            3072,
            128256
          ],
          "parameter_count": 394002432
        }
      ]
    }
  ]
}
